[
    {
        "company_name": "MLP GROUP SA",
        "content": "Zarz\u0105d MLP Group S.A. _\"Sp\u00f3\u0142ka\"_ z siedzib\u0105 w Pruszkowie w nawi\u0105zaniu do informacji\n                           o zawarciu w dniu 16 grudnia 2016 roku umowy kredytowej i umowy zabezpiecze\u0144 przez\n                           MLP Pruszk\u00f3w I Sp. z o.o. z siedziba\u0328 w Pruszkowie _\"Kredytobiorca\"_ z Raiffeisen\n                           Bank Polska S.A. z siedziba\u0328 w Warszawie _\"Bank\"_, na podstawie kt\u00f3rej Bank ma udzieli\u0107\u0301\n                           Kredytobiorcy kredytu do kwoty 38.946.000,00 EUR _\"Kredyt\"_,  informuje, i\u017c w dniu\n                           21 grudnia 2016 r. Kredytobiorca ustanowi\u0142 hipotek\u0119 umown\u0105 \u0142\u0105czn\u0105 do sumy 54.750.000,00\n                           EUR _s\u0142ownie: pi\u0119\u0107dziesi\u0105t cztery miliony siedemset pi\u0119\u0107dziesi\u0105t tysi\u0119cy euro_ oraz\n                           14.425.500 EUR _s\u0142ownie: czterna\u015bcie milion\u00f3w czterysta dwadzie\u015bcia pi\u0119\u0107 tysi\u0119cy pi\u0119\u0107set\n                           euro_ na nieruchomo\u015bciach  nale\u017c\u0105cych do Sp\u00f3\u0142ki, po\u0142o\u017conych w Pruszkowie obj\u0119tych\n                           ksi\u0119gami wieczystymi o numerach: KW nr WA1P/00036973/9, KW nr WA1P/00038589/4, KW\n                           WA1P/00038595/9, KW nr WA1P/00038590/4, KW nr WA1P/00038591/1, KW nr WA1P/00038596/6,\n                           KW nr WA1P/00038593/5, KW nr WA1P/00038590/4.Podstawa prawna:\u00a7 5 ust. 1 pkt. 1 oraz 7 Rozporz\u0105dzenia Ministra Finans\u00f3w z dnia 13 lutego 2009 r.\n                           w sprawie informacji bie\u017c\u0105cych i okresowych przekazywanych przez emitent\u00f3w papier\u00f3w\n                           warto\u015bciowych oraz warunk\u00f3w uznawania za r\u00f3wnowa\u017cne informacji wymaganych przepisami\n                           prawa pa\u0144stwa nieb\u0119d\u0105cego pa\u0144stwem cz\u0142onkowskim _Dz. U. 2009 Nr 33 poz. 259 z po\u0301z\u0301n.\n                           zm._",
        "date": "2016-12-22",
        "sentiment": -0.010554153242697154
    },
    {
        "company_name": "MLP GROUP SA",
        "content": "Zarz\u0105d MLP Group S.A. _\"Sp\u00f3\u0142ka\", \"Emitent\"_ z siedzib\u0105 w Pruszkowie, informuje o zawarciu\n                           przez jednostk\u0119 zale\u017cn\u0105 Emitenta znacz\u0105cej umowy. W dniu 16 grudnia 2016 roku MLP\n                           Pruszk\u00f3w I Sp. z o.o.  z siedzib\u0105 w Pruszkowie _\"Kredytobiorca\"_ zawar\u0142a z Raiffeisen\n                           Bank Polska S.A. z siedzib\u0105 w Warszawie _\"Bank\"_ umow\u0119 kredytow\u0105 i umowy zabezpiecze\u0144.\n                           Na podstawie podpisanej dokumentacji kredytowej, bank ma udzieli\u0107 Kredytobiorcy kredytu\n                           do kwoty 38.946.000,00 EUR _\"Kredyt\"_.Jako zabezpieczenie sp\u0142aty Kredytu, Kredytobiorca jest zobowi\u0105zany ustanowi\u0107 hipotek\u0119\n                           na wszystkich nieruchomo\u015bciach nale\u017c\u0105cych do Kredytobiorcy, o ustanowieniu tej hipoteki\n                           Kredytobiorca poinformuje w odr\u0119bnym raporcie.Kredytobiorca jako zabezpieczenie sp\u0142aty Kredytu :a_ podpisa\u0142 umow\u0119 ustanowienia zastawu rejestrowego na zbiorze rzeczy i praw nale\u017c\u0105cych\n                           do Kredytobiorcy do sumy zabezpieczenia 54.750.000,00 EUR,b_ podpisa\u0142 umow\u0119 ustanowienia zastaw\u00f3w finansowych i rejestrowych na wierzytelno\u015bciach\n                           wynikaj\u0105cych z umowy rachunku bankowego do sumy zabezpieczenia 69.179.500,00 EURc_ ustanowi\u0142 inne, zwyczajowo stosowane w finansowaniach tego typu, zabezpieczenia.\n                           Warto\u015b\u0107 zobowi\u0105zania zabezpieczonego ograniczonym prawem rzeczowym na nieruchomo\u015bciach\n                           Kredytobiorcy to 38.946.000,00 EUR. Warto\u015b\u0107 ewidencyjna udzia\u0142\u00f3w Kredytobiorcy w ksi\u0119gach\n                           rachunkowych Sp\u00f3\u0142ki to 62.663.800 PLN. Nie wyst\u0119puj\u0105 powi\u0105zania pomi\u0119dzy Emitentem i osobami zarz\u0105dzaj\u0105cymi lub nadzoruj\u0105cymi\n                           Emitenta a Bankiem, na rzecz kt\u00f3rego ustanowiono zastawy i osobami tym Bankiem zarz\u0105dzaj\u0105cymi.Kryterium b\u0119d\u0105cym podstaw\u0105 uznania aktyw\u00f3w za aktywa o znacznej warto\u015bci jest warto\u015b\u0107\n                           udzia\u0142\u00f3w Kredytobiorcy w ksi\u0119gach rachunkowych Emitenta, kt\u00f3ra to warto\u015b\u0107 przekracza\n                           10% kapita\u0142\u00f3w w\u0142asnych emitenta.Emitent posiada 100% udzia\u0142\u00f3w w kapitale zak\u0142adowym Kredytobiorcy, o warto\u015bci nominalnej\n                           62.663.800,00 PLN. Udzia\u0142y w kapitale zak\u0142adowym Kredytobiorcy s\u0105 d\u0142ugoterminow\u0105 inwestycj\u0105\n                           Emitenta. Emitent posiada 100% g\u0142os\u00f3w na zgromadzeniu wsp\u00f3lnik\u00f3w Kredytobiorcy. Umowa, o kt\u00f3rej mowa w niniejszym raporcie, nie jest umow\u0105 z podmiotem powi\u0105zanym.\n                           Umowa kredytowa zawarta zosta\u0142a na warunkach rynkowych. Pozosta\u0142e zapisy, w tym zapisy\n                           dotycz\u0105ce kar, nie odbiegaj\u0105 od zapis\u00f3w powszechnie stosowanych w tego typu umowach.Podstawa prawna:\u00a7 5 ust. 1 pkt. 1,3 oraz 7 Rozporz\u0105dzenia Ministra Finans\u00f3w z dnia 13 lutego 2009\n                           r. w sprawie informacji bie\u017c\u0105cych i okresowych przekazywanych przez emitent\u00f3w papier\u00f3w\n                           warto\u015bciowych oraz warunk\u00f3w uznawania za r\u00f3wnowa\u017cne informacji wymaganych przepisami\n                           prawa pa\u0144stwa nieb\u0119d\u0105cego pa\u0144stwem cz\u0142onkowskim _Dz. U. 2009 Nr 33 poz. 259 z p\u00f3\u017an.\n                           zm._",
        "date": "2016-12-16",
        "sentiment": -0.0001637222314909417
    },
    {
        "company_name": "MLP GROUP SA",
        "content": "Zarz\u0105d MLP Group S.A. _\"Sp\u00f3\u0142ka\"_ z siedzib\u0105 w Pruszkowie informuje, \u017ce w dniu 5 grudnia\n                           2016 r. Rada Nadzorcza Sp\u00f3\u0142ki dokona\u0142a wyboru firmy KPMG Audyt Sp\u00f3\u0142ka z ograniczon\u0105\n                           odpowiedzialno\u015bci\u0105 sp\u00f3\u0142ka komandytowa z siedzib\u0105 w Warszawie, jako podmiotu uprawnionego\n                           do zbadania jednostkowych i skonsolidowanych sprawozda\u0144 finansowych za lata: 2016\n                           i 2017, a tak\u017ce dokonania przegl\u0105du \u015br\u00f3drocznego jednostkowego i skonsolidowanego\n                           sprawozdania finansowego w roku obrotowym 2017.Sp\u00f3\u0142ka KPMG Audyt sp\u00f3\u0142ka z ograniczon\u0105 odpowiedzialno\u015bci\u0105 sp\u00f3\u0142ka komandytowa jest\n                           wpisana na list\u0119 podmiot\u00f3w uprawnionych do badania sprawozda\u0144 finansowych og\u0142oszon\u0105\n                           przez Krajow\u0105 Izb\u0119 Bieg\u0142ych Rewident\u00f3w pod numerem 3546.Sp\u00f3\u0142ka korzysta\u0142a wcze\u015bniej z us\u0142ug firmy KPMG Audyt Sp\u00f3\u0142ka z ograniczon\u0105 odpowiedzialno\u015bci\u0105\n                           sp\u00f3\u0142ka komandytowa w zakresie badania jednostkowych i skonsolidowanych rocznych sprawozda\u0144\n                           finansowych oraz przegl\u0105du \u015br\u00f3drocznych jednostkowych i skonsolidowanych sprawozda\u0144\n                           finansowych.Wyb\u00f3r zosta\u0142 dokonany zgodnie z obowi\u0105zuj\u0105cymi przepisami i normami zawodowymi.Umowa z bieg\u0142ym rewidentem zostanie zawarta przez Zarz\u0105d Sp\u00f3\u0142ki na czas niezb\u0119dny\n                           do wykonania przez bieg\u0142ego rewidenta powierzonych czynno\u015bci.Podstawa prawna:\u00a7 5 ust. 1 pkt. 19 Rozporz\u0105dzenia Ministra Finans\u00f3w z dnia 13 lutego 2009 r. w sprawie\n                           informacji bie\u017c\u0105cych i okresowych przekazywanych przez emitent\u00f3w papier\u00f3w warto\u015bciowych\n                           oraz warunk\u00f3w uznawania za r\u00f3wnowa\u017cne informacji wymaganych przepisami prawa pa\u0144stwa\n                           nieb\u0119d\u0105cego pa\u0144stwem cz\u0142onkowskim _Dz. U. 2009 Nr 33 poz. 259 z p\u00f3\u017an. zm._",
        "date": "2016-12-06",
        "sentiment": -0.014761474298393298
    },
    {
        "company_name": "MLP GROUP SA",
        "content": "Zarz\u0105d MLP GROUP S.A. _\"Sp\u00f3\u0142ka\"_ z siedzib\u0105 w Pruszkowie informuje, \u017ce w dniu 23 listopada\n                           2017 r. otrzyma\u0142 od Aegon Otwartego Funduszu Emerytalnego wpisanego do rejestru funduszy\n                           emerytalnych prowadzonego przez S\u0105d Okr\u0119gowy w Warszawie, VII Wydzia\u0142 Cywilny Rejestrowy\n                           pod numerem Rfe 13, posiadaj\u0105cego numer REGON 014889592 oraz NIP 521-31-24-415 _\"Aegon\n                           OFE\"_, jako organ kt\u00f3rego dzia\u0142a Aegon Powszechne Towarzystwo Emerytalne S.A. z siedzib\u0105\n                           w Warszawie, pod adresem ul. Wo\u0142oska 5, 02-675 Warszawa, wpisanego do rejestru przedsi\u0119biorc\u00f3w\n                           prowadzonego przez S\u0105d Rejonowy dla m.st. Warszawy w Warszawie, XIII Wydzia\u0142 Gospodarczy\n                           Krajowego Rejestru S\u0105dowego, pod nr KRS 0000028767 _\"Towarzystwo\"_, zawiadomienie,\n                           zgodnie z kt\u00f3rym, w zwi\u0105zku z zako\u0144czeniem w dniu 17 listopada 2017 roku likwidacji\n                           Nordea Otwartego Funduszu Emerytalnego _\"Nordea OFE\"_, skutkuj\u0105cym przeniesieniem\n                           w tym dniu wszystkich aktyw\u00f3w Nordea OFE do Aegon OFE oraz wst\u0105pieniem Aegon OFE we\n                           wszystkie prawa i obowi\u0105zki Nordea OFE, Aegon OFE na dzie\u0144 17 listopada 2017 roku\n                           posiada 1.149.775 akcji Sp\u00f3\u0142ki, co stanowi 6,35% udzia\u0142u w kapitale zak\u0142adowym Sp\u00f3\u0142ki\n                           i uprawnia do 1.149.775 g\u0142os\u00f3w na Walnym Zgromadzeniu Akcjonariuszy Sp\u00f3\u0142ki, co stanowi\n                           6,35% og\u00f3lnej liczby g\u0142os\u00f3w na Walnym Zgromadzeniu Akcjonariuszy Sp\u00f3\u0142ki.Bezpo\u015brednio przed dniem zako\u0144czenia likwidacji Nordea OFE: a_ Aegon OFE posiada\u0142 809.036 akcji Sp\u00f3\u0142ki, co stanowi\u0142o 4,47% udzia\u0142u w jej kapitale\n                           zak\u0142adowym i uprawnia\u0142o do 809.036 g\u0142os\u00f3w, to jest 4,47% og\u00f3lnej liczby g\u0142os\u00f3w,b_ Nordea OFE posiada\u0142 340.739 akcji Sp\u00f3\u0142ki, co stanowi\u0142o 1,88% udzia\u0142u w jej kapitale\n                           zak\u0142adowym i uprawnia\u0142o do 1,88 % g\u0142os\u00f3w, to jest 1,88% og\u00f3lnej liczby g\u0142os\u00f3w.Wed\u0142ug stanu na dzie\u0144 23 listopada 2017 roku, Aegon OFE posiada \u0142\u0105cznie 1.149.775\n                           akcji Sp\u00f3\u0142ki, co stanowi 6,35% udzia\u0142u w kapitale zak\u0142adowym i uprawnia do 1.149.775\n                           g\u0142os\u00f3w na Walnym Zgromadzeniu Akcjonariuszy Sp\u00f3\u0142ki, to jest 6,35% og\u00f3lnej liczby g\u0142os\u00f3w\n                           na Walnym Zgromadzeniu Akcjonariuszy Sp\u00f3\u0142ki.Podstawa prawna:Art. 70 ust. 1 ustawy z dnia 29 lipca 2005 roku o ofercie publicznej i warunkach wprowadzania\n                           instrument\u00f3w finansowych do zorganizowanego systemu obrotu oraz o sp\u00f3\u0142kach publicznych\n                           t.j. Dz. U. z 2013r., poz. 1382 r. z p\u00f3\u017an. zm._Art. 56 ust. 1 pkt 2 Ustawy o ofercie \u2013 informacje bie\u017c\u0105ce i okresowe.",
        "date": "2017-11-23",
        "sentiment": 0.010484475093800976
    },
    {
        "company_name": "MLP GROUP SA",
        "content": "Zarz\u0105d sp\u00f3\u0142ki MLP Group S.A. z siedzib\u0105 w Pruszkowie _\"Sp\u00f3\u0142ka\"_ informuje, i\u017c w dniu\n                           19 pa\u017adziernika 2017 r., MLP Bucharest West SRL _\"Nabywca\"_, sp\u00f3\u0142ka zale\u017cna od Sp\u00f3\u0142ki\n                           zawar\u0142a umow\u0119 nabycia nieruchomo\u015bci po\u0142o\u017conej w Rudeni Village, Chitila Town, Ilfov\n                           County w Rumunii _rumu\u0144ska nazwa : Sat Rudeni, Oras Chitila, Judet Ilfov_, o \u0142\u0105cznej\n                           powierzchni 188.045 metr\u00f3w kwadratowych, za cen\u0119 4.000.000 Euro _wraz z nak\u0142adami\n                           na tej nieruchomo\u015bci oraz instalacjami s\u0142u\u017c\u0105cymi zaopatrzeniu w energi\u0119 elektryczn\u0105_.\n                           Nieruchomo\u015b\u0107 wpisana jest do ksi\u0105g wieczystych prowadzonych w Chitila _rumu\u0144ska nazwa\n                           : Cartea Funciara Chitila_ o numerach 51425, 51426, 51427, 51428 oraz 53566.Podstaw\u0105 przekazania niniejszego raportu jest istotno\u015b\u0107 zdarzenia ze wzgl\u0119du na dzia\u0142alno\u015b\u0107\n                           Sp\u00f3\u0142ki.Podstawa prawna:art. 17. ust.1 MAR informacje poufne",
        "date": "2017-10-20",
        "sentiment": 0.0004747038983450002
    },
    {
        "company_name": "MLP GROUP SA",
        "content": "MLP Group S.A. z siedzib\u0105 w Pruszkowie _\"Sp\u00f3\u0142ka\"_ informuje, \u017ce Sp\u00f3\u0142ka otrzyma\u0142a od\n                           Thesinger Limited z siedzib\u0105 w Nikozji na Cyprze powiadomienie na podstawie art. 69\n                           ust. 2 i 4  ustawy z dnia 29 lipca 2005r. o ofercie publicznej i warunkach wprowadzania\n                           instrument\u00f3w finansowych do zorganizowanego systemu obrotu oraz o sp\u00f3\u0142kach publicznych\n                           _t.j. Dz.U. 2016, poz. 1639 ze zm._ o zmniejszeniu przez Thesinger Limited stanu posiadania\n                           akcji Sp\u00f3\u0142ki poni\u017cej progu 10% og\u00f3lnej liczby g\u0142os\u00f3w w Sp\u00f3\u0142ce. Do zmniejszenia udzia\u0142u w og\u00f3lnej liczbie g\u0142os\u00f3w dosz\u0142o w wyniku rozliczenia w dniu\n                           29 wrze\u015bnia 2017 roku transakcji przeniesienia akcji MLP Group S.A. na podstawie umowy\n                           przeniesienia _Deed of transfer_  zawartej w dniu 26 wrze\u015bnia 2017 roku _\"Transakcja\"_.\n                           Transakcja polega\u0142a na przeniesieniu 149.155 akcji Sp\u00f3\u0142ki MLP GROUP S.A. reprezentuj\u0105cych\n                           0,8% kapita\u0142u zak\u0142adowego MLP Group S.A przez THESINGER Ltd. na rzecz Pana Shimshon\u2019a\n                           Marfogel\u2019a, Przewodnicz\u0105cego Rady Nadzorczej Sp\u00f3\u0142ki i by\u0142a zawarta w zwi\u0105zku z wykonaniem\n                           programu wyp\u0142at z zysku przyj\u0119tego w dniu 31.12.2008r przez The Israel Land Development\n                           Company Ltd z siedzib\u0105 w Izraelu i aneksem do umowy o prac\u0119 z maja 2007 zawartej pomi\u0119dzy\n                           Panem Shimshon\u2019em Marfogel i The Israel Land Development Company Ltd z siedzib\u0105 w\n                           Izraelu w zamian za udzia\u0142y w sp\u00f3\u0142ce THESINGER Ltd. _vide: Aneks nr 1 do prospektu\n                           informacyjnego zatwierdzonego 7.10.2013r. przez Komisj\u0119 Nadzoru Finansowego decyzj\u0105\n                           nr DPI/WE/410/44/26/13_, o to\u017csamej warto\u015bci rynkowej. Przed zawarciem Transakcji THESINGER Limited z siedzib\u0105 w Nikozji posiada\u0142a 1.920.475\n                           akcji MLP GROUP S.A., reprezentuj\u0105cych 10,6 % kapita\u0142u zak\u0142adowego Sp\u00f3\u0142ki, uprawiaj\u0105cych\n                           do 1.920.475 g\u0142os\u00f3w na walnym zgromadzeniu, co stanowi\u0142o 10,6% og\u00f3lnej liczby g\u0142os\u00f3w.\n                           Aktualnie THESINGER Limited z siedzib\u0105 w Nikozji posiada 1.771.320 akcji MLP GROUP\n                           S.A., reprezentuj\u0105cych 9,8% kapita\u0142u zak\u0142adowego tej sp\u00f3\u0142ki, uprawiaj\u0105cych do 1.771.320\n                           g\u0142os\u00f3w na walnym zgromadzeniu, co stanowi 9,8% og\u00f3lnej liczby g\u0142os\u00f3w. Emitent za\u0142\u0105cza do niniejszego raportu otrzymane powiadomienie.Podstawa prawna: Art. 70 pkt 1 Ustawy o ofercie - nabycie lub zbycie znacznego pakietu akcji",
        "date": "2017-10-02",
        "sentiment": -0.0018373085948928255
    },
    {
        "company_name": "MLP GROUP SA",
        "content": "MLP Group S.A. z siedzib\u0105 w Pruszkowie _\"Emitent\"_ informuje, \u017ce w dniu 2 pa\u017adziernika\n                           2017 roku otrzyma\u0142 od Pana Shimshon Marfogel, Przewodnicz\u0105cego Rady Nadzorczej, uzupe\u0142nienie\n                           do powiadomienia o transakcji dokonanej przez osob\u0119 zobowi\u0105zan\u0105, o otrzymaniu kt\u00f3rego\n                           Emitent poinformowa\u0142 raportem bie\u017c\u0105cym nr 12/2017 z dnia 29.09.2017. Emitent za\u0142\u0105cza do niniejszego raportu dokument otrzymany w dniu 2 pa\u017adziernika 2017\n                           r. Podstawa prawna: art. 19 ust. 3 Rozporz\u0105dzenia MAR",
        "date": "2017-10-02",
        "sentiment": -0.0018373085948928255
    },
    {
        "company_name": "MLP GROUP SA",
        "content": "Zarz\u0105d MLP Group S.A. z siedzib\u0105 w Pruszkowie _\"Emitent\"_ informuje, \u017ce w dniu 29\n                           wrze\u015bnia 2017 roku do Emitenta wp\u0142yn\u0119\u0142o, w trybie art. 19 Rozporz\u0105dzenia MAR, powiadomienie\n                           o transakcji dokonanej przez osob\u0119 zobowi\u0105zan\u0105, Przewodnicz\u0105cego Rady Nadzorczej Emitenta\n                           \u2013 Pana Shimshon Marfogel.Tre\u015b\u0107 powiadomienia Emitent przekazuje w za\u0142\u0105czeniu.",
        "date": "2017-09-29",
        "sentiment": -0.011870276638374895
    },
    {
        "company_name": "MLP GROUP SA",
        "content": "Zarz\u0105d MLP GROUP S.A. _\"Sp\u00f3\u0142ka\"_ z siedzib\u0105 w Pruszkowie informuje, \u017ce w dniu 7 wrze\u015bnia\n                           2017 r. otrzyma\u0142 od Aegon Powszechne Towarzystwo Emerytalne S.A. z siedzib\u0105 w Warszawie,\n                           pod adresem ul. Wo\u0142oska 5, 02-675 Warszawa, wpisanego do rejestru przedsi\u0119biorc\u00f3w\n                           prowadzonego przez S\u0105d Rejonowy dla m.st. Warszawy w Warszawie, XIII Wydzia\u0142 Gospodarczy\n                           Krajowego Rejestru S\u0105dowego, pod nr KRS 0000028767 _\"Towarzystwo\"_, dotychczas zarz\u0105dzaj\u0105cego\n                           wy\u0142\u0105cznie Aegon Otwartym Funduszem Emerytalnym, wpisanym do Rejestru Funduszy Emerytalnych\n                           prowadzonego przez S\u0105d Rejonowy w Warszawie VII Wydzia\u0142 Cywilny Rejestrowy pod numerem\n                           RFe 13 _\"Aegon OFE\"_, zawiadomienie na podstawie art. 69 ust. 1 ustawy z dnia 29 lipca\n                           2005 r. o ofercie publicznej i warunkach wprowadzania instrument\u00f3w finansowych do\n                           zorganizowanego systemu obrotu oraz o sp\u00f3\u0142kach publicznych _Dz.U.05.184.1539 z p\u00f3\u017an.\n                           zmianami_, \u017ce Towarzystwo w dniu 1 wrze\u015bnia 2017 roku przej\u0119\u0142o zarz\u0105dzanie Nordea\n                           Otwartym Funduszem Emerytalnym, wpisanym do Rejestru Funduszy Emerytalnych prowadzonego\n                           przez S\u0105d Rejonowy w Warszawie VII Wydzia\u0142 Cywilny Rejestrowy pod numerem RFe 11 _\"Nordea\n                           OFE\"_, w wyniku czego \u0142\u0105czny udzia\u0142 funduszy zarz\u0105dzanych przez Towarzystwo, to jest\n                           funduszy Aegon OFE i Nordea OFE, w og\u00f3lnej liczbie g\u0142os\u00f3w na walnym zgromadzeniu Sp\u00f3\u0142ki\n                           przekroczy\u0142 5% g\u0142os\u00f3w. Przed opisanym powy\u017cej przej\u0119ciem zarz\u0105dzania Nordea OFE przez Towarzystwo: a_ Aegon OFE posiada\u0142 809 036 akcji Sp\u00f3\u0142ki, co stanowi\u0142o 4,47% udzia\u0142u w jej kapitale\n                           zak\u0142adowym i uprawnia\u0142o do 809 036 g\u0142os\u00f3w, to jest 4,47% og\u00f3lnej liczby g\u0142os\u00f3w,b_ Nordea OFE posiada\u0142 340 739 akcji Sp\u00f3\u0142ki, co stanowi\u0142o 1,88% udzia\u0142u w jej kapitale\n                           zak\u0142adowym i uprawnia\u0142o do 340 739 g\u0142os\u00f3w, to jest 1,88% og\u00f3lnej liczby g\u0142os\u00f3w.Po przej\u0119ciu przez Towarzystwo zarz\u0105dzania Nordea OFE, wed\u0142ug stanu na dzie\u0144 1 wrze\u015bnia\n                           2017 roku, oba fundusze zarz\u0105dzane przez Towarzystwo _Aegon OFE i Nordea OFE_ posiadaj\u0105\n                           \u0142\u0105cznie 1 149 775 akcji Sp\u00f3\u0142ki, co stanowi 6,35% udzia\u0142u w kapitale zak\u0142adowym i uprawnia\n                           do 1 149 775 g\u0142os\u00f3w, to jest 6,35% og\u00f3lnej liczby g\u0142os\u00f3w.Podstawa prawna: Art. 70 ust. 1 ustawy z dnia 29 lipca 2005 roku o ofercie publicznej i warunkach wprowadzania\n                           instrument\u00f3w finansowych do zorganizowanego systemu obrotu oraz o sp\u00f3\u0142kach publicznych\n                           t.j. Dz. U. z 2013r., poz. 1382 r. z p\u00f3\u017an. zm._Art. 56 ust. 1 pkt 2 Ustawy o ofercie \u2013 informacje bie\u017c\u0105ce i okresowe.",
        "date": "2017-09-07",
        "sentiment": -0.002464524846944975
    },
    {
        "company_name": "MLP GROUP SA",
        "content": "Zarz\u0105d sp\u00f3\u0142ki MLP Group S.A. _dalej: Sp\u00f3\u0142ka_ niniejszym zawiadamia o zapoznaniu si\u0119\n                           w dniu dzisiejszym z Uchwa\u0142\u0105 nr 739/2017 Zarz\u0105du Gie\u0142dy Papier\u00f3w Warto\u015bciowych w Warszawie\n                           S.A. _\"Zarz\u0105d GPW\"_ z dnia 7 lipca 2017 r. w sprawie wyznaczenia pierwszego dnia notowania\n                           w alternatywnym systemie obrotu na Catalyst obligacji na okaziciela serii A sp\u00f3\u0142ki\n                           MLP Group S.A.Zgodnie z powy\u017csz\u0105 uchwa\u0142\u0105 Zarz\u0105d GPW postanowi\u0142: 1_ okre\u015bli\u0107 dzie\u0144 12 lipca 2017 r. jako dzie\u0144 pierwszego notowania w alternatywnym\n                           systemie obrotu na Catalyst 20.000 _dwudziestu tysi\u0119cy_ obligacji na okaziciela serii\n                           A sp\u00f3\u0142ki MLP Group S.A., o warto\u015bci nominalnej 1.000 EUR _jeden tysi\u0105c euro_ ka\u017cda,\n                           oznaczonych przez Krajowy Depozyt Papier\u00f3w Warto\u015bciowych S.A. kodem \"PLMLPGR00033\",\n                           2_ notowa\u0107 obligacje, o kt\u00f3rych mowa w pkt. 1_ w systemie notowa\u0144 ci\u0105g\u0142ych pod nazw\u0105\n                           skr\u00f3con\u0105 \"MLP0522\".",
        "date": "2017-07-10",
        "sentiment": -0.08234717024089235
    },
    {
        "company_name": "MLP GROUP SA",
        "content": "Zarz\u0105d sp\u00f3\u0142ki MLP Group S.A. _dalej: Sp\u00f3\u0142ka_ informuje o powzi\u0119ciu informacji o podj\u0119ciu\n                           przez Zarz\u0105d Gie\u0142dy Papier\u00f3w Warto\u015bciowych S.A. _dalej: Gie\u0142da_ uchwa\u0142y nr 720/2017\n                           z dnia 4 lipca 2017 r., zgodnie z kt\u00f3r\u0105 Zarz\u0105d Gie\u0142dy postanowi\u0142 wprowadzi\u0107 do alternatywnego\n                           systemu obrotu na Catalyst 20.000 _dwadzie\u015bcia tysi\u0119cy_ obligacji na okaziciela serii\n                           A sp\u00f3\u0142ki MLP Group S.A. o warto\u015bci nominalnej 1.000 EUR _jeden tysi\u0105c euro_ ka\u017cda. Jednocze\u015bnie Sp\u00f3\u0142ka informuje o podj\u0119ciu przez BondSpot S.A. _dalej: BondSpot_ uchwa\u0142y\n                           nr 148/17 z dnia 4 lipca 2017 r., zgodnie z kt\u00f3r\u0105 Zarz\u0105d BondSpot postanowi\u0142 wprowadzi\u0107\n                           do alternatywnego systemu obrotu na Catalyst 20.000 _dwadzie\u015bcia tysi\u0119cy_ obligacji\n                           na okaziciela serii A sp\u00f3\u0142ki MLP Group S.A. o warto\u015bci nominalnej 1.000 EUR _jeden\n                           tysi\u0105c euro_ ka\u017cda. W/w uchwa\u0142y wchodz\u0105 w \u017cycie z dniem ich podj\u0119cia.Podstawa prawna: art. 17. ust.1 MAR informacje poufne.",
        "date": "2017-07-05",
        "sentiment": 0.00608931051131344
    },
    {
        "company_name": "MLP GROUP SA",
        "content": "Zarz\u0105d MLP GROUP S.A. z siedzib\u0105 w Pruszkowie _\"MLPG\"_ informuje, \u017ce akcjonariusze\n                           obecni na Zwyczajnym Walnym Zgromadzeniu MLPG, kt\u00f3re odby\u0142o si\u0119 w dniu 5 czerwca 2017\n                           roku, dysponowali 11.072.797 g\u0142osami. Oznacza to, \u017ce kapita\u0142 zak\u0142adowy MLPG dziel\u0105cy\n                           si\u0119 na 18.113.255 akcji, z kt\u00f3rych ka\u017cda daje prawo do jednego g\u0142osu, by\u0142 reprezentowany\n                           na ZWZ w 61,13 %.Akcjonariuszem posiadaj\u0105cym co najmniej 5% liczby g\u0142os\u00f3w na ZWZ MLPG w dniu 5 czerwca\n                           2017 roku by\u0142a: CAJAMARCA HOLLAND B.V. z siedzib\u0105 w Delft, posiadaj\u0105ca 10.319.842 g\u0142os\u00f3w, co stanowi\u0142o\n                           93,20% liczby g\u0142os\u00f3w na tym Zgromadzeniu oraz 56,97% og\u00f3lnej liczby g\u0142os\u00f3w,Podstawa prawna: Art. 70 pkt. 3_ ustawy z dnia 29 lipca 2005 r. o ofercie publicznej i warunkach wprowadzenia\n                           instrument\u00f3wfinansowych do zorganizowanego systemu obrotu oraz o sp\u00f3\u0142kach publicznych",
        "date": "2017-06-05",
        "sentiment": -0.06575563228494025
    },
    {
        "company_name": "MLP GROUP SA",
        "content": "Zarz\u0105d MLP Group S.A. _Emitent, Sp\u00f3\u0142ka_ z siedzib\u0105 w Pruszkowie podaje do wiadomo\u015bci\n                           uchwa\u0142y podj\u0119te przez Zwyczajne Walne Zgromadzenie Sp\u00f3\u0142ki w dniu 5 czerwca 2017 roku.Tre\u015b\u0107 uchwa\u0142 zawarta jest w za\u0142\u0105czniku do niniejszego raportu.Podstawa prawna: Art. 56 ust. 1 pkt 2 ustawy z dnia 29 lipca 2005 r. o ofercie publicznej i warunkach\n                           wprowadzenia instrument\u00f3w finansowych do zorganizowanego systemu obrotu oraz o sp\u00f3\u0142kach\n                           publicznych oraz \u00a738 ust. 1 pkt 7 rozporz\u0105dzenia Ministra Finans\u00f3w z dnia 19 lutego 2009 r. w sprawie\n                           informacji bie\u017c\u0105cych i okresowych przekazywanych przez emitent\u00f3w papier\u00f3w warto\u015bciowych\n                           oraz warunk\u00f3w uznawania za r\u00f3wnowa\u017cne informacji wymaganych przepisami prawa pa\u0144stwa\n                           nieb\u0119d\u0105cego pa\u0144stwem cz\u0142onkowskim.",
        "date": "2017-06-05",
        "sentiment": -0.06575563228494025
    },
    {
        "company_name": "MLP GROUP SA",
        "content": "Zarz\u0105d MLP GROUP S.A. _\"Sp\u00f3\u0142ka\"_ informuje, \u017ce w dniu 11 maja 2017 roku Sp\u00f3\u0142ka wyemitowa\u0142a\n                           w ramach oferty prywatnej 20.000 sztuk obligacji na okaziciela serii A Sp\u00f3\u0142ki o warto\u015bci\n                           nominalnej 1.000 euro ka\u017cda i \u0142\u0105cznej warto\u015bci emisyjnej 20.000.000 euro _\"Obligacje\"_.Obligacje podlegaj\u0105 zmiennemu oprocentowaniu w wysoko\u015bci stawki EURIBOR dla sze\u015bciomiesi\u0119cznych\n                           depozyt\u00f3w bankowych w EUR powi\u0119kszonej o mar\u017c\u0119.Obligacje zosta\u0142y wyemitowane jako niezabezpieczone. Cel emisji Obligacji nie zosta\u0142 okre\u015blony. Ostateczny termin wykupu Obligacji zosta\u0142 ustalony na dzie\u0144 11 maja 2022 roku z mo\u017cliwo\u015bci\u0105\n                           wcze\u015bniejszego wykupu Obligacji przez Sp\u00f3\u0142k\u0119. Obligacje nie maj\u0105 formy dokumentu. Obligacje zosta\u0142y przyj\u0119te do depozytu papier\u00f3w\n                           warto\u015bciowych przez Krajowy Depozyt Papier\u00f3w Warto\u015bciowych S.A. na podstawie uchwa\u0142y\n                           nr 305/17 Zarz\u0105du Krajowego Depozytu Papier\u00f3w Warto\u015bciowych S.A. i oznaczone kodem\n                           PLMLPGR00033.Sp\u00f3\u0142ka zamierza ubiega\u0107 si\u0119 o wprowadzenie Obligacji do obrotu w alternatywnym systemie\n                           obrotu organizowanym przez BondSpot oraz/lub GPW, o czym Sp\u00f3\u0142ka poinformuje odr\u0119bnym\n                           raportem bie\u017c\u0105cym.Podstawa prawna: art. 17. ust.1 MAR informacje poufne.",
        "date": "2017-05-12",
        "sentiment": -0.0031906476069818407
    },
    {
        "company_name": "MLP GROUP SA",
        "content": "Zarz\u0105d MLP Group S.A. z siedzib\u0105 w Pruszkowie _\"Emitent\", \"Sp\u00f3\u0142ka\"_ informuje o zawarciu\n                           przez jednostk\u0119 zale\u017cn\u0105 Emitenta znacz\u0105cej umowy. W dniu 4 kwietnia 2017 roku sp\u00f3\u0142ka\n                           MLP Logistic Park Germany I Sp. z o.o. & Co. KG z siedzib\u0105 w Dortmundzie, Niemcy _\"Kupuj\u0105cy\"_\n                           zawar\u0142a z Ortem PropCo 2 B.V. z siedzib\u0105 w Amsterdamie _\"Sprzedaj\u0105cy\"_ umow\u0119 sprzeda\u017cy\n                           nieruchomo\u015bci po\u0142o\u017conej w miejscowo\u015bci Unna w Niemczech _\"Umowa\"_.Na podstawie postanowie\u0144 Umowy, Kupuj\u0105cy jest zobowi\u0105zany zap\u0142aci\u0107 cen\u0119 sprzeda\u017cy\n                           nieruchomo\u015bci w kwocie 6.450.000 EUR w terminie 30 dni od dnia zawarcia Umowy.Nie wyst\u0119puj\u0105 powi\u0105zania pomi\u0119dzy Emitentem i osobami zarz\u0105dzaj\u0105cymi lub nadzoruj\u0105cymi\n                           Emitenta, a Sprzedaj\u0105cym ani osobami zarz\u0105dzaj\u0105cymi Sprzedaj\u0105cym.Emitent posiada 100% udzia\u0142\u00f3w w kapitale zak\u0142adowym obu wsp\u00f3lnik\u00f3w Kupuj\u0105cego, o \u0142\u0105cznej\n                           warto\u015bci nominalnej 10.000 PLN. Udzia\u0142y w kapitale zak\u0142adowym obu wsp\u00f3lnik\u00f3w Kupuj\u0105cego\n                           s\u0105 d\u0142ugoterminow\u0105 inwestycj\u0105 Emitenta. Umowa, o kt\u00f3rej mowa w niniejszym raporcie, nie jest umow\u0105 z podmiotem powi\u0105zanym.\n                           Umowa zawarta zosta\u0142a na warunkach rynkowych, jej zapisy, w tym zapisy dotycz\u0105ce kar,\n                           nie odbiegaj\u0105 od zapis\u00f3w powszechnie stosowanych w tego typu umowach.[Zarz\u0105d Emitenta podj\u0105\u0142 decyzj\u0119 o publikacji wy\u017cej wymienionych informacji z uwagi\n                           na istotn\u0105 warto\u015b\u0107 umowy i jej znaczenie dla dzia\u0142alno\u015bci Emitenta]Podstawa prawna:art. 17. ust.1 MAR informacje poufne",
        "date": "2017-04-05",
        "sentiment": 0.006301546988706315
    },
    {
        "company_name": "MLP GROUP SA",
        "content": "Zarz\u0105d MLP GROUP S.A. _\"Sp\u00f3\u0142ka\"_ informuje, \u017ce w dniu 4 kwietnia 2017 roku podj\u0105\u0142\n                           uchwa\u0142\u0119 nr 1/04/2017 w sprawie ustanowienia programu emisji obligacji na podstawie,\n                           kt\u00f3rej w dniu 4 kwietnia 2017 roku pomi\u0119dzy Sp\u00f3\u0142k\u0105, a Bankiem Polska Kasa Opieki S.A.\n                           pe\u0142ni\u0105cym funkcj\u0119 Organizatora, Agenta Emisji, Agenta ds. P\u0142atno\u015bci, Agenta Kalkulacyjnego,\n                           Dealera, Depozytariusza, Bookrunnera, sp\u00f3\u0142k\u0105 Pekao Investment Banking S.A. pe\u0142ni\u0105c\u0105\n                           funkcj\u0119 Organizatora, Agenta Technicznego, Dealera zosta\u0142a zawarta umowa programowa\n                           dotycz\u0105ca programu emisji obligacji _\"Umowa Programowa\"_.Umowa Programowa umo\u017cliwia dokonywanie emisji obligacji w seriach oferowanych w ramach\n                           oferty prywatnej, w trybie proponowania nabycia zgodnie z art. 33 pkt 2 ustawy z dnia\n                           15 stycznia 2015 r. o obligacjach.Zgodnie z Umow\u0105 Programow\u0105, Program emisji obligacji przewiduje emisj\u0119 obligacji przez\n                           Sp\u00f3\u0142k\u0119 w wielu seriach na zasadach okre\u015blonych w Umowie do kwoty 50.000.000 EUR stanowi\u0105cej\n                           maksymaln\u0105 dopuszczaln\u0105 \u0142\u0105czn\u0105 warto\u015b\u0107 wyemitowanych i niewykupionych obligacji. Obligacje emitowane zgodnie z Umow\u0105 Programow\u0105 b\u0119d\u0105 obligacjami niezabezpieczonymi,\n                           uprawniaj\u0105cymi obligatariuszy wy\u0142\u0105cznie do otrzymania \u015bwiadcze\u0144 o charakterze pieni\u0119\u017cnym.\n                           Obligacje b\u0119d\u0105 mog\u0142y zosta\u0107 wprowadzone do alternatywnego systemu obrotu prowadzonego\n                           przez Gie\u0142d\u0119 Papier\u00f3w Warto\u015bciowych w Warszawie S.A. lub BondSpot S.A. Okres zapadalno\u015bci obligacji wyemitowanych w ramach Programu b\u0119dzie nie d\u0142u\u017cszy ni\u017c\n                           10 lat. Warto\u015b\u0107 nominalna ka\u017cdej obligacji emitowanej w ramach Programu b\u0119dzie wynosi\u0107\n                           1.000 EUR lub wielokrotno\u015b\u0107 tej kwoty. Umowa Programowa zosta\u0142a zawarta na czas nieoznaczony.Szczeg\u00f3\u0142owe warunki emisji poszczeg\u00f3lnych serii obligacji b\u0119d\u0105 ka\u017cdorazowo ustalane\n                           w odpowiednich dokumentach emisyjnych.Podstawa prawna:art. 17. ust.1 MAR informacje poufne",
        "date": "2017-04-04",
        "sentiment": -0.012291238384955437
    }
]